LICENSE.txt
MANIFEST.in
README.md
README.rst
setup.py
simple_search.py
django_simple_search.egg-info/PKG-INFO
django_simple_search.egg-info/SOURCES.txt
django_simple_search.egg-info/dependency_links.txt
django_simple_search.egg-info/not-zip-safe
django_simple_search.egg-info/requires.txt
django_simple_search.egg-info/top_level.txt