Metadata-Version: 1.1
Name: django-simple-search
Version: 1.0.1
Summary: Recurring event tools for django
Home-page: https://github.com/gregplaysguitar/django-simple-search
Author: Greg Brown
Author-email: greg@gregbrown.co.nz
License: BSD License
Platform: any
Classifier: Development Status :: 5 - Production/Stable
Classifier: Environment :: Web Environment
Classifier: Intended Audience :: Developers
Classifier: Operating System :: OS Independent
Classifier: Programming Language :: Python
Classifier: Programming Language :: Python :: 2
Classifier: Programming Language :: Python :: 2.7
Classifier: Programming Language :: Python :: 3
Classifier: Programming Language :: Python :: 3.4
Classifier: Programming Language :: Python :: 3.5
Classifier: Topic :: Internet :: WWW/HTTP :: Dynamic Content
Classifier: Framework :: Django
